async_run_ollama.py
ollama_rag_run.py
ollama_run_async-0.2.5.dist-info/licenses/LICENSE
ollama_run_async-0.2.5.dist-info/METADATA
ollama_run_async-0.2.5.dist-info/WHEEL
ollama_run_async-0.2.5.dist-info/top_level.txt
ollama_run_async-0.2.5.dist-info/RECORD
