Metadata-Version: 2.4
Name: ollama-run-async
Version: 0.2.5
Summary: Functions to conveniently run asynchronous Ollama workflows, including RAG support.
Requires-Python: >=3.9
License-File: LICENSE
Requires-Dist: pandas
Requires-Dist: numpy
Requires-Dist: tqdm
Requires-Dist: ollama
Requires-Dist: nest_asyncio
Requires-Dist: langchain>=0.0.299
Requires-Dist: langchain-community>=0.0.74
Requires-Dist: faiss-cpu>=1.7.3
Requires-Dist: chromadb>=0.3.21
Dynamic: license-file
